ochi/__init__.py
ochi/cli.py
ochi/constants.py
ochi/fetch.py
ochi/models/__init__.py
ochi/models/story.py
ochi-0.0.1.dist-info/entry_points.txt
ochi-0.0.1.dist-info/LICENSE
ochi-0.0.1.dist-info/WHEEL
ochi-0.0.1.dist-info/METADATA
ochi-0.0.1.dist-info/RECORD
