Metadata-Version: 2.1
Name: ochi
Version: 0.0.1
Summary: A simple CLI to read Hacker News in the terminal.
License: MIT
Keywords: hacker-news,hackernews,cli,click
Author: daniarlert
Author-email: arlertdaniel@gmail.com
Requires-Python: >=3.10,<4.0
Classifier: License :: OSI Approved :: MIT License
Classifier: Programming Language :: Python :: 3
Classifier: Programming Language :: Python :: 3.10
Requires-Dist: asyncclick (>=8.1.3.4,<9.0.0.0)
Requires-Dist: httpx (>=0.23.0,<0.24.0)
Requires-Dist: rich (>=12.5.1,<13.0.0)
Requires-Dist: textual (>=0.1.18,<0.2.0)
